dearpyapp/__init__.py
dearpyapp/application.py
dearpyapp/colors.py
dearpyapp/themes.py
dearpyapp/utils.py
dearpyapp/components/__init__.py
dearpyapp/components/log.py
dearpyapp/components/port_control.py
dearpyapp/components/tab.py
dearpyapp-0.1.6.dist-info/LICENSE
dearpyapp-0.1.6.dist-info/METADATA
dearpyapp-0.1.6.dist-info/WHEEL
dearpyapp-0.1.6.dist-info/top_level.txt
dearpyapp-0.1.6.dist-info/RECORD
