Metadata-Version: 2.1
Name: dearpyapp
Version: 0.1.6
Summary: Wrapper for DearPyGui
Home-page: https://github.com/means0nothing/DearPyApp
Author: Pavel Shevcov
Author-email: means0nothing@gmail.com
License: MIT
Classifier: Development Status :: 3 - Alpha
Classifier: Intended Audience :: Developers
Classifier: License :: OSI Approved :: MIT License
Classifier: Operating System :: Microsoft :: Windows :: Windows 10
Classifier: Programming Language :: Python :: 3.9
Classifier: Programming Language :: Python :: 3.10
Classifier: Topic :: Software Development :: Libraries :: Python Modules
Requires-Python: >=3.9
License-File: LICENSE
Requires-Dist: dearpygui ==1.8.0
Requires-Dist: recordclass ==0.17.2
Requires-Dist: pywin32 ==304
Requires-Dist: pyperclip ==1.8.2
